kv.py
kv-0.4.1.dist-info/entry_points.txt
kv-0.4.1.dist-info/COPYING.txt
kv-0.4.1.dist-info/WHEEL
kv-0.4.1.dist-info/METADATA
kv-0.4.1.dist-info/RECORD
